migrator/__init__.py
migrator/__main__.py
migrator/cli.py
migrator/version.py
migrator/core/__init__.py
migrator/core/alembic_backend.py
migrator/core/base.py
migrator/core/config.py
migrator/core/constants.py
migrator/core/detector.py
migrator/core/logger.py
migrator/core/migration_operations.py
migrator/templates/env.py.mako
migrator/templates/script.py.mako
migrator/utils/__init__.py
migrator/utils/config_loader.py
migrator/utils/file_utils.py
migrator/utils/validators.py
migrator_cli-0.4.2.dist-info/METADATA
migrator_cli-0.4.2.dist-info/WHEEL
migrator_cli-0.4.2.dist-info/entry_points.txt
migrator_cli-0.4.2.dist-info/licenses/LICENSE
migrator_cli-0.4.2.dist-info/RECORD
