Metadata-Version: 2.4
Name: migrator-cli
Version: 0.4.2
Summary: Universal migration CLI for Python apps
Project-URL: Homepage, https://github.com/db-toolkit/migrator
Project-URL: Repository, https://github.com/db-toolkit/migrator
Project-URL: Issues, https://github.com/db-toolkit/migrator/issues
Project-URL: Changelog, https://github.com/db-toolkit/migrator/blob/main/CHANGELOG.md
Author-email: Peter Adelodun <adelodunpeter24@gmail.com>
License: MIT
License-File: LICENSE
Keywords: alembic,cli,database,migration,orm,sqlalchemy
Classifier: Development Status :: 5 - Production/Stable
Classifier: Intended Audience :: Developers
Classifier: License :: OSI Approved :: MIT License
Classifier: Programming Language :: Python :: 3
Classifier: Programming Language :: Python :: 3.9
Classifier: Programming Language :: Python :: 3.10
Classifier: Programming Language :: Python :: 3.11
Classifier: Programming Language :: Python :: 3.12
Classifier: Programming Language :: Python :: 3.13
Classifier: Topic :: Database
Classifier: Topic :: Software Development :: Libraries :: Python Modules
Requires-Python: >=3.9
Requires-Dist: alembic>=1.13.0
Requires-Dist: mako>=1.3.0
Requires-Dist: psycopg2-binary>=2.9.0
Requires-Dist: pydantic>=2.0.0
Requires-Dist: python-dotenv>=1.0.0
Requires-Dist: pyyaml>=6.0
Requires-Dist: rich>=13.0.0
Requires-Dist: sqlalchemy>=2.0.0
Requires-Dist: typer>=0.9.0
